{
  "slug": "coconut-almond-cookies",
  "title": "Coconut Almond Cookies",
  "seed_keyword": "coconut almond cookies",
  "keywords": {
    "all": [
      {
        "keyword": "almond joy cookies",
        "volume": 6600,
        "competition": 7
      },
      {
        "keyword": "almond joy cookie recipe",
        "volume": 4400,
        "competition": 1
      },
      {
        "keyword": "coconut almond cookies",
        "volume": 1000,
        "competition": 27
      },
      {
        "keyword": "almond and coconut cookies",
        "volume": 1000,
        "competition": 27
      },
      {
        "keyword": "joy cookies",
        "volume": 1000,
        "competition": 12
      },
      {
        "keyword": "almond and coconut flour cookies",
        "volume": 480,
        "competition": 4
      },
      {
        "keyword": "almond coconut flour cookies",
        "volume": 480,
        "competition": 4
      },
      {
        "keyword": "almond flour and coconut flour cookies",
        "volume": 480,
        "competition": 4
      },
      {
        "keyword": "almond flour coconut flour cookies",
        "volume": 480,
        "competition": 4
      },
      {
        "keyword": "coconut flour keto cookie",
        "volume": 480,
        "competition": 5
      },
      {
        "keyword": "coconut macaroon almonds",
        "volume": 320,
        "competition": 17
      },
      {
        "keyword": "almond and coconut macaroons",
        "volume": 320,
        "competition": 17
      },
      {
        "keyword": "almond coconut macaroon",
        "volume": 320,
        "competition": 17
      },
      {
        "keyword": "coconut oreos thins",
        "volume": 320,
        "competition": 26
      },
      {
        "keyword": "almond meal and coconut cookies",
        "volume": 260,
        "competition": 1
      },
      {
        "keyword": "almond meal coconut cookies",
        "volume": 260,
        "competition": 1
      },
      {
        "keyword": "coconut flakes cookies",
        "volume": 260,
        "competition": 26
      },
      {
        "keyword": "macaroons flour",
        "volume": 260,
        "competition": 26
      },
      {
        "keyword": "almond coconut chocolate chip cookies",
        "volume": 170,
        "competition": 4
      },
      {
        "keyword": "almond coconut cookie recipe",
        "volume": 170,
        "competition": 1
      },
      {
        "keyword": "coconut flour cookies vegan",
        "volume": 170,
        "competition": 0
      },
      {
        "keyword": "almond flour and coconut oil cookies",
        "volume": 140,
        "competition": 0
      },
      {
        "keyword": "almond flour coconut oil cookies",
        "volume": 140,
        "competition": 0
      },
      {
        "keyword": "coconut flour healthy cookies",
        "volume": 110,
        "competition": 3
      },
      {
        "keyword": "keto chocolate chip cookies coconut flour",
        "volume": 110,
        "competition": 0
      },
      {
        "keyword": "key lime coconut cookies",
        "volume": 110,
        "competition": 68
      }
    ]
  },
  "processed": false
}