{
  "slug": "quick-pickled-shallots",
  "title": "Quick Pickled Shallots",
  "seed_keywords": [
    "pickled shallots",
    "pickled vegetables",
    "vinegar pickled onions",
    "homemade pickled condiments",
    "quick pickle recipe"
  ],
  "keywords": {
    "all": [
      {
        "keyword": "red onions",
        "volume": 135000,
        "competition": 12
      },
      {
        "keyword": "red pickled onions",
        "volume": 135000,
        "competition": 29
      },
      {
        "keyword": "pickling cucumbers",
        "volume": 110000,
        "competition": 29
      },
      {
        "keyword": "onion pickle",
        "volume": 110000,
        "competition": 44
      },
      {
        "keyword": "cucumber and pickles",
        "volume": 110000,
        "competition": 29
      },
      {
        "keyword": "pickle is a cucumber",
        "volume": 110000,
        "competition": 29
      },
      {
        "keyword": "pickled red onion recipe",
        "volume": 74000,
        "competition": 17
      },
      {
        "keyword": "pickled radish",
        "volume": 40500,
        "competition": 28
      },
      {
        "keyword": "pickled onion recipe",
        "volume": 40500,
        "competition": 14
      },
      {
        "keyword": "pickled banana peppers",
        "volume": 40500,
        "competition": 13
      },
      {
        "keyword": "quick pickled red onions",
        "volume": 40500,
        "competition": 13
      },
      {
        "keyword": "fast pickled red onions",
        "volume": 40500,
        "competition": 13
      },
      {
        "keyword": "pickle and onion recipe",
        "volume": 40500,
        "competition": 14
      },
      {
        "keyword": "pickled onion dishes",
        "volume": 40500,
        "competition": 14
      },
      {
        "keyword": "fridge pickled cucumbers",
        "volume": 33100,
        "competition": 11
      },
      {
        "keyword": "refrigerator cucumber pickles",
        "volume": 33100,
        "competition": 11
      },
      {
        "keyword": "pickled peppers",
        "volume": 27100,
        "competition": 55
      },
      {
        "keyword": "pickled daikon radish",
        "volume": 27100,
        "competition": 15
      },
      {
        "keyword": "daikon pickle",
        "volume": 27100,
        "competition": 15
      },
      {
        "keyword": "pickled carrots",
        "volume": 22200,
        "competition": 63
      },
      {
        "keyword": "pickled cabbage",
        "volume": 22200,
        "competition": 32
      },
      {
        "keyword": "pink onions",
        "volume": 22200,
        "competition": 7
      },
      {
        "keyword": "pickled red cabbage",
        "volume": 14800,
        "competition": 20
      },
      {
        "keyword": "carrot and daikon",
        "volume": 12100,
        "competition": 9
      },
      {
        "keyword": "quick pickle",
        "volume": 12100,
        "competition": 3
      },
      {
        "keyword": "quick pickled onions",
        "volume": 12100,
        "competition": 11
      },
      {
        "keyword": "carrot daikon",
        "volume": 12100,
        "competition": 9
      },
      {
        "keyword": "cucumber quick pickle",
        "volume": 12100,
        "competition": 1
      },
      {
        "keyword": "fast cucumber pickle",
        "volume": 12100,
        "competition": 1
      },
      {
        "keyword": "fast pickle",
        "volume": 12100,
        "competition": 3
      },
      {
        "keyword": "fast pickled cucumber",
        "volume": 12100,
        "competition": 1
      },
      {
        "keyword": "fast pickles cucumbers",
        "volume": 12100,
        "competition": 1
      },
      {
        "keyword": "instant pickled onions",
        "volume": 12100,
        "competition": 11
      },
      {
        "keyword": "pickled onions how to",
        "volume": 12100,
        "competition": 16
      },
      {
        "keyword": "quick marinated cucumbers",
        "volume": 12100,
        "competition": 1
      },
      {
        "keyword": "quick pickle for cucumbers",
        "volume": 12100,
        "competition": 1
      },
      {
        "keyword": "quick pickle recipe",
        "volume": 9900,
        "competition": 4
      },
      {
        "keyword": "chinese mustard greens pickled",
        "volume": 9900,
        "competition": 58
      },
      {
        "keyword": "fast pickle recipe",
        "volume": 9900,
        "competition": 4
      },
      {
        "keyword": "mustard green pickle",
        "volume": 9900,
        "competition": 58
      },
      {
        "keyword": "quick cucumber pickle recipe",
        "volume": 9900,
        "competition": 4
      },
      {
        "keyword": "kirby cucumber",
        "volume": 8100,
        "competition": 56
      },
      {
        "keyword": "mixed pickles",
        "volume": 8100,
        "competition": 64
      },
      {
        "keyword": "crisp okra pickles",
        "volume": 8100,
        "competition": 2
      },
      {
        "keyword": "pickled veggie recipe",
        "volume": 8100,
        "competition": 4
      },
      {
        "keyword": "pickled shallots",
        "volume": 6600,
        "competition": 28
      },
      {
        "keyword": "easy pickle recipe",
        "volume": 6600,
        "competition": 5
      },
      {
        "keyword": "best pickled onions recipe",
        "volume": 6600,
        "competition": 4
      },
      {
        "keyword": "kirby cucumbers for pickling",
        "volume": 6600,
        "competition": 5
      },
      {
        "keyword": "making pickled cabbage",
        "volume": 6600,
        "competition": 0
      }
    ]
  },
  "seo_done": false,
  "content_done": false
}