{
  "slug": "souffle-blueberry-dutch-baby",
  "title": "Soufflé Blueberry Dutch Baby",
  "seed_keywords": [
    "blueberry dutch baby",
    "dutch baby pancake",
    "cast iron skillet breakfast",
    "egg flour batter",
    "blueberry breakfast casserole"
  ],
  "keywords": {
    "all": [
      {
        "keyword": "blueberry french toast casserole",
        "volume": 5400,
        "competition": 1
      },
      {
        "keyword": "blueberry and cream cheese french toast casserole",
        "volume": 1300,
        "competition": 1
      },
      {
        "keyword": "blueberry french toast casserole with cream cheese",
        "volume": 1300,
        "competition": 1
      },
      {
        "keyword": "overnight french toast blueberry",
        "volume": 1300,
        "competition": 1
      },
      {
        "keyword": "blueberry breakfast casserole",
        "volume": 1000,
        "competition": 1
      },
      {
        "keyword": "croissant blueberry breakfast bake",
        "volume": 880,
        "competition": 0
      },
      {
        "keyword": "blueberry breakfast bake",
        "volume": 720,
        "competition": 2
      },
      {
        "keyword": "fried chicken egg flour",
        "volume": 720,
        "competition": 1
      },
      {
        "keyword": "blueberry pancake breakfast casserole",
        "volume": 590,
        "competition": 1
      },
      {
        "keyword": "blueberry pancake casserole",
        "volume": 590,
        "competition": 1
      },
      {
        "keyword": "blueberry casserole",
        "volume": 480,
        "competition": 1
      },
      {
        "keyword": "blueberry croissant breakfast casserole",
        "volume": 390,
        "competition": 0
      },
      {
        "keyword": "blueberry cinnamon roll casserole",
        "volume": 320,
        "competition": 0
      },
      {
        "keyword": "breakfast cast iron skillet recipes",
        "volume": 320,
        "competition": 1
      },
      {
        "keyword": "breakfast recipes in a cast iron skillet",
        "volume": 320,
        "competition": 1
      },
      {
        "keyword": "breakfast skillet recipe cast iron",
        "volume": 320,
        "competition": 1
      },
      {
        "keyword": "egg flour batter",
        "volume": 260,
        "competition": 0
      },
      {
        "keyword": "blueberry breakfast casserole with cream cheese",
        "volume": 260,
        "competition": 1
      },
      {
        "keyword": "blueberry cream cheese breakfast bake",
        "volume": 260,
        "competition": 1
      },
      {
        "keyword": "blueberry cream cheese breakfast casserole",
        "volume": 260,
        "competition": 1
      },
      {
        "keyword": "blueberry croissant casserole",
        "volume": 260,
        "competition": 0
      },
      {
        "keyword": "breakfast casserole with blueberries and cream cheese",
        "volume": 260,
        "competition": 1
      },
      {
        "keyword": "egg and flour batter",
        "volume": 260,
        "competition": 0
      },
      {
        "keyword": "breakfast cast iron",
        "volume": 170,
        "competition": 17
      },
      {
        "keyword": "blueberry buttermilk pancake casserole",
        "volume": 110,
        "competition": 0
      },
      {
        "keyword": "blueberry french toast crock pot",
        "volume": 110,
        "competition": 0
      },
      {
        "keyword": "easy blueberry french toast casserole",
        "volume": 110,
        "competition": 0
      },
      {
        "keyword": "egg and flour batter for fish",
        "volume": 110,
        "competition": 0
      },
      {
        "keyword": "overnight blueberry french toast taste of home",
        "volume": 110,
        "competition": 0
      }
    ]
  },
  "seo_done": false,
  "content_done": false
}