{
  "slug": "soy-bean-drink-remix",
  "title": "Soy Bean Drink Remix",
  "seed_keywords": [
    "homemade soy milk",
    "soy bean drink",
    "coconut milk beverage",
    "soybeans blended drink",
    "asian plant based milk"
  ],
  "keywords": {
    "all": [
      {
        "keyword": "unsweetened coconut juice",
        "volume": 40500,
        "competition": 49
      },
      {
        "keyword": "coconut milk coffee",
        "volume": 6600,
        "competition": 73
      },
      {
        "keyword": "soy bean drink",
        "volume": 4400,
        "competition": 76
      },
      {
        "keyword": "soya bean drinks",
        "volume": 4400,
        "competition": 76
      },
      {
        "keyword": "coconut water lactation",
        "volume": 3600,
        "competition": 5
      },
      {
        "keyword": "silk unsweet coconutmilk",
        "volume": 1900,
        "competition": 30
      },
      {
        "keyword": "yeo's soy milk",
        "volume": 1300,
        "competition": 73
      },
      {
        "keyword": "yeo's soy bean milk",
        "volume": 1300,
        "competition": 73
      },
      {
        "keyword": "homemade soy milk",
        "volume": 1000,
        "competition": 23
      },
      {
        "keyword": "coconut drink starbucks",
        "volume": 1000,
        "competition": 1
      },
      {
        "keyword": "homemade soya bean milk",
        "volume": 1000,
        "competition": 23
      },
      {
        "keyword": "coconut water and milk",
        "volume": 720,
        "competition": 56
      },
      {
        "keyword": "prepare soya milk",
        "volume": 720,
        "competition": 1
      },
      {
        "keyword": "soy bean juice",
        "volume": 720,
        "competition": 32
      },
      {
        "keyword": "coconut beverage",
        "volume": 590,
        "competition": 78
      },
      {
        "keyword": "soybean milk drink",
        "volume": 590,
        "competition": 66
      },
      {
        "keyword": "coconut milk drink starbucks",
        "volume": 480,
        "competition": 4
      },
      {
        "keyword": "starbucks coffee coconut milk",
        "volume": 480,
        "competition": 4
      },
      {
        "keyword": "make soy milk",
        "volume": 390,
        "competition": 49
      },
      {
        "keyword": "coconut coffee starbucks",
        "volume": 390,
        "competition": 64
      },
      {
        "keyword": "coconut milk iced coffee",
        "volume": 390,
        "competition": 5
      },
      {
        "keyword": "iced coconut milk coffee",
        "volume": 390,
        "competition": 5
      },
      {
        "keyword": "make soy milk from soybeans",
        "volume": 390,
        "competition": 49
      },
      {
        "keyword": "making soymilk",
        "volume": 390,
        "competition": 49
      },
      {
        "keyword": "strawberry coconut drink starbucks",
        "volume": 390,
        "competition": 9
      },
      {
        "keyword": "turmeric and coconut milk drink",
        "volume": 390,
        "competition": 15
      },
      {
        "keyword": "turmeric coconut milk drink",
        "volume": 390,
        "competition": 15
      },
      {
        "keyword": "canned coconut milk drink",
        "volume": 320,
        "competition": 11
      },
      {
        "keyword": "canned coconut milk for coffee",
        "volume": 320,
        "competition": 30
      },
      {
        "keyword": "coconut beverage starbucks",
        "volume": 320,
        "competition": 3
      },
      {
        "keyword": "coconut beverage trader joe's",
        "volume": 320,
        "competition": 36
      },
      {
        "keyword": "coconut refresher starbucks",
        "volume": 320,
        "competition": 2
      },
      {
        "keyword": "vita coco drink",
        "volume": 260,
        "competition": 73
      },
      {
        "keyword": "chinese coconut milk drink",
        "volume": 260,
        "competition": 31
      },
      {
        "keyword": "coconut juice milk",
        "volume": 260,
        "competition": 70
      },
      {
        "keyword": "coconut milk and coconut water",
        "volume": 260,
        "competition": 77
      },
      {
        "keyword": "coconut milk coconut water",
        "volume": 260,
        "competition": 77
      },
      {
        "keyword": "coconut milk juice",
        "volume": 260,
        "competition": 70
      },
      {
        "keyword": "coconut milk with coconut water",
        "volume": 260,
        "competition": 77
      },
      {
        "keyword": "homemade soy milk yogurt",
        "volume": 260,
        "competition": 5
      },
      {
        "keyword": "homemade soy yogurt",
        "volume": 260,
        "competition": 5
      },
      {
        "keyword": "coconut milk refresher starbucks",
        "volume": 210,
        "competition": 3
      },
      {
        "keyword": "diy soy milk",
        "volume": 210,
        "competition": 33
      },
      {
        "keyword": "homemade soy milk recipe",
        "volume": 210,
        "competition": 11
      },
      {
        "keyword": "starbucks refresher coconut milk",
        "volume": 210,
        "competition": 3
      },
      {
        "keyword": "starbucks refresher with coconut milk",
        "volume": 210,
        "competition": 3
      },
      {
        "keyword": "coco royal coconut milk drink",
        "volume": 170,
        "competition": 40
      },
      {
        "keyword": "coconut milk coffee near me",
        "volume": 170,
        "competition": 20
      },
      {
        "keyword": "coconut milk hot drink",
        "volume": 170,
        "competition": 7
      },
      {
        "keyword": "drinho soya bean milk",
        "volume": 170,
        "competition": 76
      }
    ]
  },
  "seo_done": false,
  "content_done": false
}