{
  "slug": "warm-fish-green-bean-salad",
  "title": "Warm Fish Green Bean Salad",
  "seed_keywords": [
    "warm fish salad",
    "snapper green beans",
    "grilled fish dinner",
    "sautéed fish vegetables",
    "mediterranean seafood salad"
  ],
  "keywords": {
    "all": [
      {
        "keyword": "grilled salmon meals",
        "volume": 40500,
        "competition": 11
      },
      {
        "keyword": "fish recipe grill",
        "volume": 9900,
        "competition": 4
      },
      {
        "keyword": "grilled fish meals",
        "volume": 9900,
        "competition": 4
      },
      {
        "keyword": "bonefish grill dinner menu",
        "volume": 2400,
        "competition": 2
      },
      {
        "keyword": "recipes for grilled fish tacos",
        "volume": 1600,
        "competition": 4
      },
      {
        "keyword": "bonefish grill dinner for 2 special",
        "volume": 720,
        "competition": 0
      },
      {
        "keyword": "recipes for grilled seafood",
        "volume": 720,
        "competition": 9
      },
      {
        "keyword": "best fish recipes for the grill",
        "volume": 590,
        "competition": 8
      },
      {
        "keyword": "best recipe for grilled fish",
        "volume": 590,
        "competition": 8
      },
      {
        "keyword": "bonefish dinner menu with prices",
        "volume": 590,
        "competition": 1
      },
      {
        "keyword": "bonefish grill dinner menu with prices",
        "volume": 590,
        "competition": 1
      },
      {
        "keyword": "good fish recipes on the grill",
        "volume": 590,
        "competition": 8
      },
      {
        "keyword": "easy fish recipes on the grill",
        "volume": 390,
        "competition": 6
      },
      {
        "keyword": "sword fish dinner",
        "volume": 390,
        "competition": 1
      },
      {
        "keyword": "grilled salmon dinner",
        "volume": 320,
        "competition": 3
      },
      {
        "keyword": "warm fish salad",
        "volume": 260,
        "competition": 0
      },
      {
        "keyword": "mediterranean seafood salad",
        "volume": 260,
        "competition": 4
      },
      {
        "keyword": "grilled fish dinner",
        "volume": 140,
        "competition": 1
      },
      {
        "keyword": "bonefish dinner",
        "volume": 140,
        "competition": 4
      },
      {
        "keyword": "grilled salmon dinner ideas",
        "volume": 110,
        "competition": 6
      }
    ]
  },
  "seo_done": false,
  "content_done": false
}