{
  "slug": "zesty-citrus-lemonade",
  "title": "Zesty Citrus Lemonade",
  "seed_keywords": [
    "homemade lemonade",
    "fresh squeezed citrus",
    "vegan citrus drinks",
    "citrus simple syrup",
    "orange lemon juice"
  ],
  "keywords": {
    "all": [
      {
        "keyword": "howto make lemonade",
        "volume": 49500,
        "competition": 5
      },
      {
        "keyword": "homemade lemonade",
        "volume": 27100,
        "competition": 9
      },
      {
        "keyword": "home made lemonade",
        "volume": 27100,
        "competition": 9
      },
      {
        "keyword": "handmade lemonade",
        "volume": 27100,
        "competition": 9
      },
      {
        "keyword": "limonade homemade",
        "volume": 27100,
        "competition": 9
      },
      {
        "keyword": "homemade lemonade recipe",
        "volume": 22200,
        "competition": 10
      },
      {
        "keyword": "recipe for home made lemonade",
        "volume": 22200,
        "competition": 10
      },
      {
        "keyword": "fresh lemonade",
        "volume": 9900,
        "competition": 21
      },
      {
        "keyword": "fresh lemonade juice",
        "volume": 8100,
        "competition": 64
      },
      {
        "keyword": "best lemonade recipe",
        "volume": 6600,
        "competition": 4
      },
      {
        "keyword": "good recipes for lemonade",
        "volume": 6600,
        "competition": 4
      },
      {
        "keyword": "great lemonade recipes",
        "volume": 6600,
        "competition": 4
      },
      {
        "keyword": "perfect lemonade recipe",
        "volume": 6600,
        "competition": 4
      },
      {
        "keyword": "fresh lemonade recipe",
        "volume": 5400,
        "competition": 19
      },
      {
        "keyword": "easy lemonade recipe",
        "volume": 5400,
        "competition": 5
      },
      {
        "keyword": "lemonade lemon juice recipe",
        "volume": 4400,
        "competition": 9
      },
      {
        "keyword": "recipe for lemonade made with lemon juice",
        "volume": 4400,
        "competition": 9
      },
      {
        "keyword": "make lemonade",
        "volume": 3600,
        "competition": 9
      },
      {
        "keyword": "homemade strawberry lemonade",
        "volume": 2400,
        "competition": 6
      },
      {
        "keyword": "homemade strawberry lemonade recipe",
        "volume": 2400,
        "competition": 6
      },
      {
        "keyword": "simple lemonade recipe",
        "volume": 1900,
        "competition": 5
      },
      {
        "keyword": "easy lemonade",
        "volume": 1900,
        "competition": 15
      },
      {
        "keyword": "easy simple lemonade recipe",
        "volume": 1900,
        "competition": 5
      },
      {
        "keyword": "fresh squeezed lemonade recipe",
        "volume": 1600,
        "competition": 14
      },
      {
        "keyword": "homemade lemonade with lemon juice",
        "volume": 1600,
        "competition": 8
      },
      {
        "keyword": "homemade lemonade recipe lemon juice",
        "volume": 1600,
        "competition": 8
      },
      {
        "keyword": "homemade lemonade using lemon juice",
        "volume": 1600,
        "competition": 8
      },
      {
        "keyword": "lemonade recipe fresh squeezed",
        "volume": 1600,
        "competition": 14
      },
      {
        "keyword": "best home made lemonade",
        "volume": 1000,
        "competition": 7
      },
      {
        "keyword": "best homemade lemonade",
        "volume": 1000,
        "competition": 7
      },
      {
        "keyword": "lemon and orange juice",
        "volume": 880,
        "competition": 4
      },
      {
        "keyword": "lemonade recipe real lemons",
        "volume": 880,
        "competition": 2
      },
      {
        "keyword": "orange juice and lemon",
        "volume": 880,
        "competition": 4
      },
      {
        "keyword": "make lemonade with lemon juice",
        "volume": 720,
        "competition": 6
      },
      {
        "keyword": "lemon juice orange juice",
        "volume": 720,
        "competition": 12
      },
      {
        "keyword": "orange juice and lemon juice",
        "volume": 720,
        "competition": 12
      },
      {
        "keyword": "easy homemade lemonade",
        "volume": 590,
        "competition": 5
      },
      {
        "keyword": "best homemade lemonade recipe",
        "volume": 590,
        "competition": 6
      },
      {
        "keyword": "easy home made lemonade",
        "volume": 590,
        "competition": 5
      },
      {
        "keyword": "home made lemonade easy",
        "volume": 590,
        "competition": 5
      },
      {
        "keyword": "home made pink lemonade",
        "volume": 590,
        "competition": 3
      },
      {
        "keyword": "lemonade homemade easy",
        "volume": 590,
        "competition": 5
      },
      {
        "keyword": "lemonade recipe fresh lemons",
        "volume": 590,
        "competition": 21
      },
      {
        "keyword": "orange lemon and lime",
        "volume": 590,
        "competition": 4
      },
      {
        "keyword": "diy lemonade",
        "volume": 480,
        "competition": 6
      },
      {
        "keyword": "home made lemonade recipe",
        "volume": 480,
        "competition": 9
      },
      {
        "keyword": "home made lemonade with lemons",
        "volume": 480,
        "competition": 14
      },
      {
        "keyword": "healthy homemade lemonade",
        "volume": 390,
        "competition": 3
      },
      {
        "keyword": "healthy homemade lemonade recipe",
        "volume": 390,
        "competition": 3
      },
      {
        "keyword": "homemade lemonade juice",
        "volume": 390,
        "competition": 8
      }
    ]
  },
  "seo_done": false,
  "content_done": false
}